{"guide_features.md":"DCcwRDQw","guide_features_bulk-create.md":"DrRcEEAd","guide_features_change-color.md":"CNtsXhEq","guide_features_create-tag.md":"DVUMfXSz","guide_features_export.md":"CtB2C5jL","guide_features_input-candidates.md":"D0penSry","guide_features_keyword-details.md":"DmoMtDtJ","guide_features_keyword-total.md":"C1whvCE9","guide_features_mtg-total.md":"B700SO2e","guide_features_period-details.md":"B8bWmUHB","guide_features_replace-title.md":"DqvJW48L","guide_features_settings.md":"oraLIl9I","guide_features_sidebar-visibility.md":"njGbtVAu","guide_features_time-badge.md":"B1zqrdeC","guide_features_update-calculation.md":"zj5xOsFZ","guide_installation.md":"CiJJbc9C","guide_jobcan.md":"BfSbJOMm","guide_team.md":"Xoem6xcx","guide_team_bulk-create.md":"oLW9FtdI","guide_team_details.md":"DWi0ax-T","guide_team_export.md":"C4B8nrAC","guide_team_group-management.md":"BWebQRoG","guide_team_settings.md":"CupauUEx","guide_team_tag-management.md":"C7scrLWr","guide_team_team-calendar.md":"CIVVPOlf","index.md":"C_skzp-g"}
